ussa1976/__init__.py
ussa1976/__main__.py
ussa1976/_version.py
ussa1976/constants.py
ussa1976/core.py
ussa1976/py.typed
ussa1976-0.3.3.dist-info/WHEEL
ussa1976-0.3.3.dist-info/METADATA
ussa1976-0.3.3.dist-info/LICENSE.rst
ussa1976-0.3.3.dist-info/entry_points.txt
ussa1976-0.3.3.dist-info/RECORD
