Metadata-Version: 2.1
Name: ussa1976
Version: 0.3.3
Summary: The U.S. Standard Atmosphere 1976 model.
Home-page: https://github.com/nollety/ussa1976
License: MIT
Author: Yvan Nollet
Author-email: yvan.nollet@rayference.eu
Requires-Python: >=3.8,<3.10
Classifier: License :: OSI Approved :: MIT License
Classifier: Programming Language :: Python :: 3
Classifier: Programming Language :: Python :: 3.8
Classifier: Programming Language :: Python :: 3.9
Classifier: Programming Language :: Python :: 3.8
Classifier: Programming Language :: Python :: 3.9
Requires-Dist: click (>=7.0)
Requires-Dist: netCDF4 (>=1.5.7)
Requires-Dist: numpy (>=1.22)
Requires-Dist: scipy (>=1.6.3)
Requires-Dist: xarray (>=0.18.2)
Project-URL: Changelog, https://github.com/nollety/ussa1976/releases
Project-URL: Documentation, https://ussa1976.readthedocs.io
Project-URL: Repository, https://github.com/nollety/ussa1976
